cdk_certbot_dns_route53/__init__.py
cdk_certbot_dns_route53/py.typed
cdk_certbot_dns_route53/_jsii/__init__.py
cdk_certbot_dns_route53/_jsii/cdk-certbot-dns-route53@2.4.698.jsii.tgz
cdk_certbot_dns_route53-2.4.698.dist-info/LICENSE
cdk_certbot_dns_route53-2.4.698.dist-info/METADATA
cdk_certbot_dns_route53-2.4.698.dist-info/WHEEL
cdk_certbot_dns_route53-2.4.698.dist-info/top_level.txt
cdk_certbot_dns_route53-2.4.698.dist-info/RECORD
