Metadata-Version: 2.1
Name: cdk-certbot-dns-route53
Version: 2.4.698
Summary: Create Cron Job Via Lambda, to update certificate and put it to S3 Bucket.
Home-page: https://github.com/neilkuan/cdk-certbot-dns-route53.git
Author: Neil Kuan<guan840912@gmail.com>
License: Apache-2.0
Project-URL: Source, https://github.com/neilkuan/cdk-certbot-dns-route53.git
Classifier: Intended Audience :: Developers
Classifier: Operating System :: OS Independent
Classifier: Programming Language :: JavaScript
Classifier: Programming Language :: Python :: 3 :: Only
Classifier: Programming Language :: Python :: 3.9
Classifier: Programming Language :: Python :: 3.10
Classifier: Programming Language :: Python :: 3.11
Classifier: Typing :: Typed
Classifier: Development Status :: 5 - Production/Stable
Classifier: License :: OSI Approved
Requires-Python: ~=3.9
License-File: LICENSE
Requires-Dist: aws-cdk-lib <3.0.0,>=2.214.1
Requires-Dist: aws-cdk.aws-lambda-python-alpha ==2.214.1.a0
Requires-Dist: constructs <11.0.0,>=10.0.5
Requires-Dist: jsii <2.0.0,>=1.125.0
Requires-Dist: publication >=0.0.3
Requires-Dist: typeguard ==2.13.3
